LICENSE
MANIFEST.in
README.md
VERSION
requirements.txt
setup.cfg
setup.py
horus_oag_sdk/__init__.py
horus_oag_sdk/api.py
horus_oag_sdk/bucket.py
horus_oag_sdk/constants.py
horus_oag_sdk/exceptions.py
horus_oag_sdk/models.py
horus_oag_sdk.egg-info/PKG-INFO
horus_oag_sdk.egg-info/SOURCES.txt
horus_oag_sdk.egg-info/dependency_links.txt
horus_oag_sdk.egg-info/requires.txt
horus_oag_sdk.egg-info/top_level.txt
horus_oag_sdk.egg-info/zip-safe
horus_oag_sdk/openapi_v3/__init__.py
horus_oag_sdk/openapi_v3/oas_body_parser.py
horus_oag_sdk/openapi_v3/oas_common.py
horus_oag_sdk/openapi_v3/oas_schema_comparator.py
horus_oag_sdk/openapi_v3/oas_schema_merger.py
horus_oag_sdk/openapi_v3/oas_schema_searcher.py