Metadata-Version: 2.1
Name: horus-oag-sdk
Version: 1.0.5
Summary: Horus OAG SDK
Home-page: https://github.com/horus4apis/horus-oag-sdk
Author: 42Crunch Research Team
Author-email: dev@42crunch.com
License: License :: OSI Approved :: GNU Affero General Public License v3 or later (AGPLv3+)
Platform: UNKNOWN
Classifier: License :: OSI Approved :: GNU Affero General Public License v3 or later (AGPLv3+)
Classifier: Programming Language :: Python :: 3.10
Classifier: Programming Language :: Python :: 3.11
Classifier: Environment :: Console
Classifier: Operating System :: POSIX
Classifier: Operating System :: MacOS
Classifier: Operating System :: OS Independent
Classifier: Operating System :: Microsoft :: Windows
